[
  {
    "username": "admin",
    "password": "240be518fabd2724ddb6f04eeb1da5967448d7e831c08c8fa822809f74c720a9",
    "name": "System Administrator",
    "email": "admin@portal.edu",
    "user_id": "ADM001",
    "user_type": "Admin",
    "last_login": "2025-07-27T23:50:02.860682",
    "admin_id": "ADM001",
    "access_level": "full",
    "system_logs": [
      {
        "log_id": "LOG20250727225913138",
        "user_id": "ADM001",
        "action": "create_user_Student",
        "details": "Created Student account for studentt (ID: STU202507275650)",
        "timestamp": "2025-07-27T22:59:13.525359"
      },
      {
        "log_id": "LOG20250727232700579",
        "user_id": "ADM001",
        "action": "create_user_Teacher",
        "details": "Created Teacher account for teacher16 (ID: TEA202507270705)",
        "timestamp": "2025-07-27T23:27:00.050409"
      },
      {
        "log_id": "LOG20250727233012222",
        "user_id": "ADM001",
        "action": "create_user_Teacher",
        "details": "Created Teacher account for teacher17 (ID: TEA202507277218)",
        "timestamp": "2025-07-27T23:30:12.447285"
      },
      {
        "log_id": "LOG20250727233219945",
        "user_id": "ADM001",
        "action": "create_user_Student",
        "details": "Created Student account for 1 (ID: STU202507272843)",
        "timestamp": "2025-07-27T23:32:19.913764"
      },
      {
        "log_id": "LOG20250727234220265",
        "user_id": "ADM001",
        "action": "create_user_Student",
        "details": "Created Student account for Test Student (ID: STU202507275199)",
        "timestamp": "2025-07-27T23:42:20.729704"
      },
      {
        "log_id": "LOG20250727235048297",
        "user_id": "ADM001",
        "action": "create_user_Teacher",
        "details": "Created Teacher account for teacher18 (ID: TEA202507275948)",
        "timestamp": "2025-07-27T23:50:48.935057"
      }
    ],
    "created_users": [
      {
        "user_id": "STU202507275650",
        "username": "student275650",
        "password": "aPKQ6yOb",
        "name": "studentt",
        "email": "studentt@uol.pk",
        "user_type": "Student",
        "created_by": "ADM001",
        "created_date": "2025-07-27T22:59:13.525330",
        "student_id": "STU202507275650"
      },
      {
        "user_id": "TEA202507270705",
        "username": "teacher270705",
        "password": "Od1duXb1",
        "name": "teacher16",
        "email": "teacher16@gmail.com",
        "user_type": "Teacher",
        "created_by": "ADM001",
        "created_date": "2025-07-27T23:27:00.050378",
        "teacher_id": "TEA202507270705",
        "department": "english",
        "salary": 84000.0
      },
      {
        "user_id": "TEA202507277218",
        "username": "teacher277218",
        "password": "SA9SrrHM",
        "name": "teacher17",
        "email": "teacher17@gmail.com",
        "user_type": "Teacher",
        "created_by": "ADM001",
        "created_date": "2025-07-27T23:30:12.447253",
        "teacher_id": "TEA202507277218",
        "department": "computer",
        "salary": -24000.0
      },
      {
        "user_id": "STU202507272843",
        "username": "student272843",
        "password": "I7qe7RKa",
        "name": "1",
        "email": "1",
        "user_type": "Student",
        "created_by": "ADM001",
        "created_date": "2025-07-27T23:32:19.913740",
        "student_id": "STU202507272843"
      },
      {
        "user_id": "STU202507275199",
        "username": "student275199",
        "password": "IGJfCyBd",
        "name": "Test Student",
        "email": "teststudent@example.com",
        "user_type": "Student",
        "created_by": "ADM001",
        "created_date": "2025-07-27T23:42:20.729683",
        "student_id": "STU202507275199"
      },
      {
        "user_id": "TEA202507275948",
        "username": "teacher275948",
        "password": "HrM6Otc6",
        "name": "teacher18",
        "email": "teacher18@gmail.com",
        "user_type": "Teacher",
        "created_by": "ADM001",
        "created_date": "2025-07-27T23:50:48.935029",
        "teacher_id": "TEA202507275948",
        "department": "arts",
        "salary": 10000000.0
      }
    ]
  },
  {
    "username": "student1",
    "password": "9b8769a4a742959a2d0298c36fb70623f2dfacda8436237df08d8dfd5b37374c",
    "name": "Student 1",
    "email": "student1@portal.edu",
    "user_id": "STU001",
    "user_type": "Student",
    "last_login": null,
    "student_id": "STU001",
    "enrolled_courses": [
      "MATH101",
      "CS102",
      "ENG101"
    ],
    "academic_records": {
      "Fall 2023": {
        "courses_grades": {
          "CS101": "A",
          "MATH101": "B+",
          "ENG101": "A-"
        },
        "cgpa": 3.67,
        "date_added": "2025-07-27T18:18:54.018736"
      },
      "Spring 2024": {
        "courses_grades": {
          "CS102": "A-",
          "MATH102": "A",
          "PHYS101": "B"
        },
        "cgpa": 3.78,
        "date_added": "2025-07-27T18:18:54.018747"
      }
    },
    "cgpa_history": [
      {
        "semester": "Fall 2023",
        "cgpa": 3.67,
        "date": "2025-07-27T18:18:54.018742"
      },
      {
        "semester": "Spring 2024",
        "cgpa": 3.78,
        "date": "2025-07-27T18:18:54.018749"
      }
    ],
    "semester_data": {
      "Fall 2023": {
        "total_courses": 3,
        "grades": {
          "CS101": "A",
          "MATH101": "B+",
          "ENG101": "A-"
        },
        "cgpa": 3.67
      },
      "Spring 2024": {
        "total_courses": 3,
        "grades": {
          "CS102": "A-",
          "MATH102": "A",
          "PHYS101": "B"
        },
        "cgpa": 3.78
      }
    }
  },
  {
    "username": "student2",
    "password": "9b8769a4a742959a2d0298c36fb70623f2dfacda8436237df08d8dfd5b37374c",
    "name": "Student 2",
    "email": "student2@portal.edu",
    "user_id": "STU002",
    "user_type": "Student",
    "last_login": null,
    "student_id": "STU002",
    "enrolled_courses": [
      "CS101",
      "MATH101",
      "PHYS101"
    ],
    "academic_records": {
      "Fall 2023": {
        "courses_grades": {
          "CS101": "A",
          "MATH101": "B+",
          "ENG101": "A-"
        },
        "cgpa": 3.67,
        "date_added": "2025-07-27T18:18:54.018761"
      },
      "Spring 2024": {
        "courses_grades": {
          "CS102": "A-",
          "MATH102": "A",
          "PHYS101": "B"
        },
        "cgpa": 3.78,
        "date_added": "2025-07-27T18:18:54.018768"
      }
    },
    "cgpa_history": [
      {
        "semester": "Fall 2023",
        "cgpa": 3.67,
        "date": "2025-07-27T18:18:54.018763"
      },
      {
        "semester": "Spring 2024",
        "cgpa": 3.78,
        "date": "2025-07-27T18:18:54.018769"
      }
    ],
    "semester_data": {
      "Fall 2023": {
        "total_courses": 3,
        "grades": {
          "CS101": "A",
          "MATH101": "B+",
          "ENG101": "A-"
        },
        "cgpa": 3.67
      },
      "Spring 2024": {
        "total_courses": 3,
        "grades": {
          "CS102": "A-",
          "MATH102": "A",
          "PHYS101": "B"
        },
        "cgpa": 3.78
      }
    }
  },
  {
    "username": "student3",
    "password": "9b8769a4a742959a2d0298c36fb70623f2dfacda8436237df08d8dfd5b37374c",
    "name": "Student 3",
    "email": "student3@portal.edu",
    "user_id": "STU003",
    "user_type": "Student",
    "last_login": null,
    "student_id": "STU003",
    "enrolled_courses": [
      "CS102",
      "MATH102",
      "BUS101"
    ],
    "academic_records": {
      "Fall 2023": {
        "courses_grades": {
          "CS101": "A",
          "MATH101": "B+",
          "ENG101": "A-"
        },
        "cgpa": 3.67,
        "date_added": "2025-07-27T18:18:54.018779"
      },
      "Spring 2024": {
        "courses_grades": {
          "CS102": "A-",
          "MATH102": "A",
          "PHYS101": "B"
        },
        "cgpa": 3.78,
        "date_added": "2025-07-27T18:18:54.018783"
      }
    },
    "cgpa_history": [
      {
        "semester": "Fall 2023",
        "cgpa": 3.67,
        "date": "2025-07-27T18:18:54.018780"
      },
      {
        "semester": "Spring 2024",
        "cgpa": 3.78,
        "date": "2025-07-27T18:18:54.018784"
      }
    ],
    "semester_data": {
      "Fall 2023": {
        "total_courses": 3,
        "grades": {
          "CS101": "A",
          "MATH101": "B+",
          "ENG101": "A-"
        },
        "cgpa": 3.67
      },
      "Spring 2024": {
        "total_courses": 3,
        "grades": {
          "CS102": "A-",
          "MATH102": "A",
          "PHYS101": "B"
        },
        "cgpa": 3.78
      }
    }
  },
  {
    "username": "student4",
    "password": "9b8769a4a742959a2d0298c36fb70623f2dfacda8436237df08d8dfd5b37374c",
    "name": "Student 4",
    "email": "student4@portal.edu",
    "user_id": "STU004",
    "user_type": "Student",
    "last_login": null,
    "student_id": "STU004",
    "enrolled_courses": [
      "CS101",
      "ENG101",
      "BUS101"
    ],
    "academic_records": {
      "Fall 2023": {
        "courses_grades": {
          "CS101": "A",
          "MATH101": "B+",
          "ENG101": "A-"
        },
        "cgpa": 3.67,
        "date_added": "2025-07-27T18:18:54.018790"
      },
      "Spring 2024": {
        "courses_grades": {
          "CS102": "A-",
          "MATH102": "A",
          "PHYS101": "B"
        },
        "cgpa": 3.78,
        "date_added": "2025-07-27T18:18:54.018794"
      }
    },
    "cgpa_history": [
      {
        "semester": "Fall 2023",
        "cgpa": 3.67,
        "date": "2025-07-27T18:18:54.018792"
      },
      {
        "semester": "Spring 2024",
        "cgpa": 3.78,
        "date": "2025-07-27T18:18:54.018795"
      }
    ],
    "semester_data": {
      "Fall 2023": {
        "total_courses": 3,
        "grades": {
          "CS101": "A",
          "MATH101": "B+",
          "ENG101": "A-"
        },
        "cgpa": 3.67
      },
      "Spring 2024": {
        "total_courses": 3,
        "grades": {
          "CS102": "A-",
          "MATH102": "A",
          "PHYS101": "B"
        },
        "cgpa": 3.78
      }
    }
  },
  {
    "username": "student5",
    "password": "9b8769a4a742959a2d0298c36fb70623f2dfacda8436237df08d8dfd5b37374c",
    "name": "Student 5",
    "email": "student5@portal.edu",
    "user_id": "STU005",
    "user_type": "Student",
    "last_login": null,
    "student_id": "STU005",
    "enrolled_courses": [
      "MATH101",
      "PHYS101",
      "ENG101"
    ],
    "academic_records": {
      "Fall 2023": {
        "courses_grades": {
          "CS101": "A",
          "MATH101": "B+",
          "ENG101": "A-"
        },
        "cgpa": 3.67,
        "date_added": "2025-07-27T18:18:54.018801"
      },
      "Spring 2024": {
        "courses_grades": {
          "CS102": "A-",
          "MATH102": "A",
          "PHYS101": "B"
        },
        "cgpa": 3.78,
        "date_added": "2025-07-27T18:18:54.018804"
      }
    },
    "cgpa_history": [
      {
        "semester": "Fall 2023",
        "cgpa": 3.67,
        "date": "2025-07-27T18:18:54.018802"
      },
      {
        "semester": "Spring 2024",
        "cgpa": 3.78,
        "date": "2025-07-27T18:18:54.018805"
      }
    ],
    "semester_data": {
      "Fall 2023": {
        "total_courses": 3,
        "grades": {
          "CS101": "A",
          "MATH101": "B+",
          "ENG101": "A-"
        },
        "cgpa": 3.67
      },
      "Spring 2024": {
        "total_courses": 3,
        "grades": {
          "CS102": "A-",
          "MATH102": "A",
          "PHYS101": "B"
        },
        "cgpa": 3.78
      }
    }
  },
  {
    "username": "student6",
    "password": "9b8769a4a742959a2d0298c36fb70623f2dfacda8436237df08d8dfd5b37374c",
    "name": "Student 6",
    "email": "student6@portal.edu",
    "user_id": "STU006",
    "user_type": "Student",
    "last_login": null,
    "student_id": "STU006",
    "enrolled_courses": [],
    "academic_records": {},
    "cgpa_history": [],
    "semester_data": {}
  },
  {
    "username": "student7",
    "password": "9b8769a4a742959a2d0298c36fb70623f2dfacda8436237df08d8dfd5b37374c",
    "name": "Student 7",
    "email": "student7@portal.edu",
    "user_id": "STU007",
    "user_type": "Student",
    "last_login": null,
    "student_id": "STU007",
    "enrolled_courses": [],
    "academic_records": {},
    "cgpa_history": [],
    "semester_data": {}
  },
  {
    "username": "student8",
    "password": "9b8769a4a742959a2d0298c36fb70623f2dfacda8436237df08d8dfd5b37374c",
    "name": "Student 8",
    "email": "student8@portal.edu",
    "user_id": "STU008",
    "user_type": "Student",
    "last_login": null,
    "student_id": "STU008",
    "enrolled_courses": [],
    "academic_records": {},
    "cgpa_history": [],
    "semester_data": {}
  },
  {
    "username": "student9",
    "password": "9b8769a4a742959a2d0298c36fb70623f2dfacda8436237df08d8dfd5b37374c",
    "name": "Student 9",
    "email": "student9@portal.edu",
    "user_id": "STU009",
    "user_type": "Student",
    "last_login": null,
    "student_id": "STU009",
    "enrolled_courses": [
      "ENG101",
      "MATH102"
    ],
    "academic_records": {},
    "cgpa_history": [],
    "semester_data": {}
  },
  {
    "username": "student10",
    "password": "9b8769a4a742959a2d0298c36fb70623f2dfacda8436237df08d8dfd5b37374c",
    "name": "Student 10",
    "email": "student10@portal.edu",
    "user_id": "STU010",
    "user_type": "Student",
    "last_login": null,
    "student_id": "STU010",
    "enrolled_courses": [],
    "academic_records": {},
    "cgpa_history": [],
    "semester_data": {}
  },
  {
    "username": "student11",
    "password": "9b8769a4a742959a2d0298c36fb70623f2dfacda8436237df08d8dfd5b37374c",
    "name": "Student 11",
    "email": "student11@portal.edu",
    "user_id": "STU011",
    "user_type": "Student",
    "last_login": null,
    "student_id": "STU011",
    "enrolled_courses": [],
    "academic_records": {},
    "cgpa_history": [],
    "semester_data": {}
  },
  {
    "username": "student12",
    "password": "9b8769a4a742959a2d0298c36fb70623f2dfacda8436237df08d8dfd5b37374c",
    "name": "Student 12",
    "email": "student12@portal.edu",
    "user_id": "STU012",
    "user_type": "Student",
    "last_login": null,
    "student_id": "STU012",
    "enrolled_courses": [],
    "academic_records": {},
    "cgpa_history": [],
    "semester_data": {}
  },
  {
    "username": "student13",
    "password": "9b8769a4a742959a2d0298c36fb70623f2dfacda8436237df08d8dfd5b37374c",
    "name": "Student 13",
    "email": "student13@portal.edu",
    "user_id": "STU013",
    "user_type": "Student",
    "last_login": null,
    "student_id": "STU013",
    "enrolled_courses": [],
    "academic_records": {},
    "cgpa_history": [],
    "semester_data": {}
  },
  {
    "username": "student14",
    "password": "9b8769a4a742959a2d0298c36fb70623f2dfacda8436237df08d8dfd5b37374c",
    "name": "Student 14",
    "email": "student14@portal.edu",
    "user_id": "STU014",
    "user_type": "Student",
    "last_login": null,
    "student_id": "STU014",
    "enrolled_courses": [],
    "academic_records": {},
    "cgpa_history": [],
    "semester_data": {}
  },
  {
    "username": "student15",
    "password": "9b8769a4a742959a2d0298c36fb70623f2dfacda8436237df08d8dfd5b37374c",
    "name": "Student 15",
    "email": "student15@portal.edu",
    "user_id": "STU015",
    "user_type": "Student",
    "last_login": null,
    "student_id": "STU015",
    "enrolled_courses": [],
    "academic_records": {},
    "cgpa_history": [],
    "semester_data": {}
  },
  {
    "username": "teacher1",
    "password": "63cb9c6fa2d65784658539a93ad47f2274a02ddff344537beb97bd399938ad22",
    "name": "teacher1",
    "email": "teacher1@gmail.com",
    "user_id": "TCH001",
    "user_type": "Teacher",
    "last_login": null,
    "teacher_id": "TCH001",
    "department": "computer science",
    "qualification": "ms",
    "contact_info": {
      "office_building": "Science Building",
      "office_hours": "Mon-Wed 2-4 PM",
      "office_room": "Room 203, Computer Building",
      "office_phone": "1234-5678"
    },
    "salary": 76000,
    "courses_taught": [],
    "salary_slips": [
      {
        "slip_id": "SS202501TCH001",
        "teacher_id": "TCH001",
        "month": "January",
        "year": 2025,
        "basic_salary": 76000,
        "allowances": {
          "Housing Allowance": 11400.0,
          "Transport Allowance": 500.0,
          "Medical Allowance": 300.0
        },
        "deductions": {
          "Tax": 9120.0,
          "Insurance": 150.0,
          "Pension": 3800.0
        },
        "net_salary": 75130.0,
        "generated_date": "2025-07-27T22:02:03.457676"
      },
      {
        "slip_id": "SS202502TCH001",
        "teacher_id": "TCH001",
        "month": "February",
        "year": 2025,
        "basic_salary": 76000,
        "allowances": {
          "Housing Allowance": 11400.0,
          "Transport Allowance": 500.0,
          "Medical Allowance": 300.0
        },
        "deductions": {
          "Tax": 9120.0,
          "Insurance": 150.0,
          "Pension": 3800.0
        },
        "net_salary": 75130.0,
        "generated_date": "2025-07-27T22:02:03.457686"
      },
      {
        "slip_id": "SS202503TCH001",
        "teacher_id": "TCH001",
        "month": "March",
        "year": 2025,
        "basic_salary": 76000,
        "allowances": {
          "Housing Allowance": 11400.0,
          "Transport Allowance": 500.0,
          "Medical Allowance": 300.0
        },
        "deductions": {
          "Tax": 9120.0,
          "Insurance": 150.0,
          "Pension": 3800.0
        },
        "net_salary": 75130.0,
        "generated_date": "2025-07-27T22:02:03.457691"
      },
      {
        "slip_id": "SS202504TCH001",
        "teacher_id": "TCH001",
        "month": "April",
        "year": 2025,
        "basic_salary": 76000,
        "allowances": {
          "Housing Allowance": 11400.0,
          "Transport Allowance": 500.0,
          "Medical Allowance": 300.0
        },
        "deductions": {
          "Tax": 9120.0,
          "Insurance": 150.0,
          "Pension": 3800.0
        },
        "net_salary": 75130.0,
        "generated_date": "2025-07-27T22:02:03.457694"
      }
    ],
    "profile_updates": [
      {
        "field": "name",
        "old_value": "Professor 1",
        "new_value": "Talha",
        "timestamp": "2025-07-27T18:36:53.459185"
      },
      {
        "field": "department",
        "old_value": "Computer Science",
        "new_value": "personal department",
        "timestamp": "2025-07-27T18:37:24.087359"
      },
      {
        "field": "qualification",
        "old_value": "PhD",
        "new_value": "chlo bhago",
        "timestamp": "2025-07-27T18:37:46.071367"
      },
      {
        "field": "email",
        "old_value": "teacher1@portal.edu",
        "new_value": "talhatalhatalhachlobhago@gmail.com",
        "timestamp": "2025-07-27T18:38:27.882515"
      },
      {
        "field": "name",
        "old_value": "Talha",
        "new_value": "professor1",
        "timestamp": "2025-07-27T18:59:48.110301"
      },
      {
        "field": "department",
        "old_value": "personal department",
        "new_value": "mathematics",
        "timestamp": "2025-07-27T19:00:02.072531"
      },
      {
        "field": "contact_info",
        "old_value": {
          "office_building": "Science Building",
          "office_hours": "Mon-Wed 2-4 PM",
          "personal_phone": "123456"
        },
        "new_value": {
          "personal_phone": "123456"
        },
        "timestamp": "2025-07-27T19:52:43.704299"
      },
      {
        "field": "qualification",
        "old_value": "chlo bhago",
        "new_value": "phd",
        "timestamp": "2025-07-27T19:53:40.353899"
      },
      {
        "field": "email",
        "old_value": "talhatalhatalhachlobhago@gmail.com",
        "new_value": "teacher1@gmail.com",
        "timestamp": "2025-07-27T19:53:58.226599"
      },
      {
        "field": "contact_info",
        "old_value": {
          "office_building": "Science Building",
          "office_hours": "Mon-Wed 2-4 PM",
          "personal_phone": "123456",
          "office_room": "Room 201, Computer Building",
          "office_phone": "1234-5678"
        },
        "new_value": {
          "office_room": "Room 202, Computer Building"
        },
        "timestamp": "2025-07-27T20:13:44.219742"
      },
      {
        "field": "contact_info",
        "old_value": {
          "office_building": "Science Building",
          "office_hours": "Mon-Wed 2-4 PM",
          "personal_phone": "123456",
          "office_room": "Room 201, Computer Building",
          "office_phone": "1234-5678"
        },
        "new_value": {
          "office_phone": "1234-5678"
        },
        "timestamp": "2025-07-27T20:14:26.907408"
      },
      {
        "field": "contact_info",
        "old_value": {
          "office_building": "Science Building",
          "office_hours": "Mon-Wed 2-4 PM",
          "personal_phone": "123456",
          "office_room": "Room 201, Computer Building",
          "office_phone": "1234-5678"
        },
        "new_value": {
          "office_room": "Room 201, Computer Building"
        },
        "timestamp": "2025-07-27T20:20:29.550437"
      },
      {
        "field": "name",
        "old_value": "professor1",
        "new_value": "teacher1",
        "timestamp": "2025-07-27T21:53:20.532816"
      },
      {
        "field": "department",
        "old_value": "mathematics",
        "new_value": "computer science",
        "timestamp": "2025-07-27T21:53:33.771993"
      },
      {
        "field": "qualification",
        "old_value": "phd",
        "new_value": "ms",
        "timestamp": "2025-07-27T21:53:58.962214"
      },
      {
        "field": "email",
        "old_value": "teacher1@gmail.com",
        "new_value": "teacher1@gmail.com",
        "timestamp": "2025-07-27T21:54:35.439564"
      },
      {
        "field": "contact_info",
        "old_value": {
          "office_building": "Science Building",
          "office_hours": "Mon-Wed 2-4 PM",
          "office_room": "Room 203, Computer Building",
          "office_phone": "1234-5678"
        },
        "new_value": {
          "years": "2 years"
        },
        "timestamp": "2025-07-27T21:56:08.474581"
      },
      {
        "field": "contact_info",
        "old_value": {
          "office_building": "Science Building",
          "office_hours": "Mon-Wed 2-4 PM",
          "office_room": "Room 203, Computer Building",
          "office_phone": "1234-5678"
        },
        "new_value": {
          "office_room": "Room 203, Computer Building"
        },
        "timestamp": "2025-07-27T21:57:20.102131"
      }
    ]
  },
  {
    "username": "teacher2",
    "password": "63cb9c6fa2d65784658539a93ad47f2274a02ddff344537beb97bd399938ad22",
    "name": "Professor 2",
    "email": "teacher2@portal.edu",
    "user_id": "TCH002",
    "user_type": "Teacher",
    "last_login": null,
    "teacher_id": "TCH002",
    "department": "Mathematics",
    "qualification": "PhD",
    "contact_info": {
      "office_room": "Room 102",
      "office_building": "Math Building",
      "office_hours": "Mon-Wed 2-4 PM",
      "personal_phone": "555-1002"
    },
    "salary": 77000,
    "courses_taught": [],
    "salary_slips": [
      {
        "slip_id": "SS202501TCH002",
        "teacher_id": "TCH002",
        "month": "January",
        "year": 2025,
        "basic_salary": 77000,
        "allowances": {
          "Housing Allowance": 11550.0,
          "Transport Allowance": 500.0,
          "Medical Allowance": 300.0
        },
        "deductions": {
          "Tax": 9240.0,
          "Insurance": 150.0,
          "Pension": 3850.0
        },
        "net_salary": 76110.0,
        "generated_date": "2025-07-27T22:02:03.457735"
      },
      {
        "slip_id": "SS202502TCH002",
        "teacher_id": "TCH002",
        "month": "February",
        "year": 2025,
        "basic_salary": 77000,
        "allowances": {
          "Housing Allowance": 11550.0,
          "Transport Allowance": 500.0,
          "Medical Allowance": 300.0
        },
        "deductions": {
          "Tax": 9240.0,
          "Insurance": 150.0,
          "Pension": 3850.0
        },
        "net_salary": 76110.0,
        "generated_date": "2025-07-27T22:02:03.457742"
      },
      {
        "slip_id": "SS202503TCH002",
        "teacher_id": "TCH002",
        "month": "March",
        "year": 2025,
        "basic_salary": 77000,
        "allowances": {
          "Housing Allowance": 11550.0,
          "Transport Allowance": 500.0,
          "Medical Allowance": 300.0
        },
        "deductions": {
          "Tax": 9240.0,
          "Insurance": 150.0,
          "Pension": 3850.0
        },
        "net_salary": 76110.0,
        "generated_date": "2025-07-27T22:02:03.457749"
      },
      {
        "slip_id": "SS202504TCH002",
        "teacher_id": "TCH002",
        "month": "April",
        "year": 2025,
        "basic_salary": 77000,
        "allowances": {
          "Housing Allowance": 11550.0,
          "Transport Allowance": 500.0,
          "Medical Allowance": 300.0
        },
        "deductions": {
          "Tax": 9240.0,
          "Insurance": 150.0,
          "Pension": 3850.0
        },
        "net_salary": 76110.0,
        "generated_date": "2025-07-27T22:02:03.457751"
      }
    ],
    "profile_updates": []
  },
  {
    "username": "teacher3",
    "password": "63cb9c6fa2d65784658539a93ad47f2274a02ddff344537beb97bd399938ad22",
    "name": "Professor 3",
    "email": "teacher3@portal.edu",
    "user_id": "TCH003",
    "user_type": "Teacher",
    "last_login": null,
    "teacher_id": "TCH003",
    "department": "Physics",
    "qualification": "PhD",
    "contact_info": {
      "office_room": "Room 103",
      "office_building": "Physics Lab",
      "office_hours": "Mon-Wed 2-4 PM",
      "personal_phone": "555-1003"
    },
    "salary": 78000,
    "courses_taught": [],
    "salary_slips": [
      {
        "slip_id": "SS202501TCH003",
        "teacher_id": "TCH003",
        "month": "January",
        "year": 2025,
        "basic_salary": 78000,
        "allowances": {
          "Housing Allowance": 11700.0,
          "Transport Allowance": 500.0,
          "Medical Allowance": 300.0
        },
        "deductions": {
          "Tax": 9360.0,
          "Insurance": 150.0,
          "Pension": 3900.0
        },
        "net_salary": 77090.0,
        "generated_date": "2025-07-27T22:02:03.457789"
      },
      {
        "slip_id": "SS202502TCH003",
        "teacher_id": "TCH003",
        "month": "February",
        "year": 2025,
        "basic_salary": 78000,
        "allowances": {
          "Housing Allowance": 11700.0,
          "Transport Allowance": 500.0,
          "Medical Allowance": 300.0
        },
        "deductions": {
          "Tax": 9360.0,
          "Insurance": 150.0,
          "Pension": 3900.0
        },
        "net_salary": 77090.0,
        "generated_date": "2025-07-27T22:02:03.457794"
      },
      {
        "slip_id": "SS202503TCH003",
        "teacher_id": "TCH003",
        "month": "March",
        "year": 2025,
        "basic_salary": 78000,
        "allowances": {
          "Housing Allowance": 11700.0,
          "Transport Allowance": 500.0,
          "Medical Allowance": 300.0
        },
        "deductions": {
          "Tax": 9360.0,
          "Insurance": 150.0,
          "Pension": 3900.0
        },
        "net_salary": 77090.0,
        "generated_date": "2025-07-27T22:02:03.457797"
      },
      {
        "slip_id": "SS202504TCH003",
        "teacher_id": "TCH003",
        "month": "April",
        "year": 2025,
        "basic_salary": 78000,
        "allowances": {
          "Housing Allowance": 11700.0,
          "Transport Allowance": 500.0,
          "Medical Allowance": 300.0
        },
        "deductions": {
          "Tax": 9360.0,
          "Insurance": 150.0,
          "Pension": 3900.0
        },
        "net_salary": 77090.0,
        "generated_date": "2025-07-27T22:02:03.457799"
      }
    ],
    "profile_updates": []
  },
  {
    "username": "teacher4",
    "password": "63cb9c6fa2d65784658539a93ad47f2274a02ddff344537beb97bd399938ad22",
    "name": "Professor 4",
    "email": "teacher4@portal.edu",
    "user_id": "TCH004",
    "user_type": "Teacher",
    "last_login": null,
    "teacher_id": "TCH004",
    "department": "English",
    "qualification": "PhD",
    "contact_info": {
      "office_room": "Room 104",
      "office_building": "Liberal Arts",
      "office_hours": "Mon-Wed 2-4 PM",
      "personal_phone": "555-1004"
    },
    "salary": 79000,
    "courses_taught": [],
    "salary_slips": [
      {
        "slip_id": "SS202501TCH004",
        "teacher_id": "TCH004",
        "month": "January",
        "year": 2025,
        "basic_salary": 79000,
        "allowances": {
          "Housing Allowance": 11850.0,
          "Transport Allowance": 500.0,
          "Medical Allowance": 300.0
        },
        "deductions": {
          "Tax": 9480.0,
          "Insurance": 150.0,
          "Pension": 3950.0
        },
        "net_salary": 78070.0,
        "generated_date": "2025-07-27T22:02:03.457854"
      },
      {
        "slip_id": "SS202502TCH004",
        "teacher_id": "TCH004",
        "month": "February",
        "year": 2025,
        "basic_salary": 79000,
        "allowances": {
          "Housing Allowance": 11850.0,
          "Transport Allowance": 500.0,
          "Medical Allowance": 300.0
        },
        "deductions": {
          "Tax": 9480.0,
          "Insurance": 150.0,
          "Pension": 3950.0
        },
        "net_salary": 78070.0,
        "generated_date": "2025-07-27T22:02:03.457861"
      },
      {
        "slip_id": "SS202503TCH004",
        "teacher_id": "TCH004",
        "month": "March",
        "year": 2025,
        "basic_salary": 79000,
        "allowances": {
          "Housing Allowance": 11850.0,
          "Transport Allowance": 500.0,
          "Medical Allowance": 300.0
        },
        "deductions": {
          "Tax": 9480.0,
          "Insurance": 150.0,
          "Pension": 3950.0
        },
        "net_salary": 78070.0,
        "generated_date": "2025-07-27T22:02:03.457865"
      },
      {
        "slip_id": "SS202504TCH004",
        "teacher_id": "TCH004",
        "month": "April",
        "year": 2025,
        "basic_salary": 79000,
        "allowances": {
          "Housing Allowance": 11850.0,
          "Transport Allowance": 500.0,
          "Medical Allowance": 300.0
        },
        "deductions": {
          "Tax": 9480.0,
          "Insurance": 150.0,
          "Pension": 3950.0
        },
        "net_salary": 78070.0,
        "generated_date": "2025-07-27T22:02:03.457867"
      }
    ],
    "profile_updates": []
  },
  {
    "username": "teacher5",
    "password": "63cb9c6fa2d65784658539a93ad47f2274a02ddff344537beb97bd399938ad22",
    "name": "Professor 5",
    "email": "teacher5@portal.edu",
    "user_id": "TCH005",
    "user_type": "Teacher",
    "last_login": null,
    "teacher_id": "TCH005",
    "department": "Business",
    "qualification": "PhD",
    "contact_info": {
      "office_room": "Room 105",
      "office_building": "Business Center",
      "office_hours": "Mon-Wed 2-4 PM",
      "personal_phone": "555-1005"
    },
    "salary": 80000,
    "courses_taught": [],
    "salary_slips": [
      {
        "slip_id": "SS202501TCH005",
        "teacher_id": "TCH005",
        "month": "January",
        "year": 2025,
        "basic_salary": 80000,
        "allowances": {
          "Housing Allowance": 12000.0,
          "Transport Allowance": 500.0,
          "Medical Allowance": 300.0
        },
        "deductions": {
          "Tax": 9600.0,
          "Insurance": 150.0,
          "Pension": 4000.0
        },
        "net_salary": 79050.0,
        "generated_date": "2025-07-27T22:02:03.457923"
      },
      {
        "slip_id": "SS202502TCH005",
        "teacher_id": "TCH005",
        "month": "February",
        "year": 2025,
        "basic_salary": 80000,
        "allowances": {
          "Housing Allowance": 12000.0,
          "Transport Allowance": 500.0,
          "Medical Allowance": 300.0
        },
        "deductions": {
          "Tax": 9600.0,
          "Insurance": 150.0,
          "Pension": 4000.0
        },
        "net_salary": 79050.0,
        "generated_date": "2025-07-27T22:02:03.457930"
      },
      {
        "slip_id": "SS202503TCH005",
        "teacher_id": "TCH005",
        "month": "March",
        "year": 2025,
        "basic_salary": 80000,
        "allowances": {
          "Housing Allowance": 12000.0,
          "Transport Allowance": 500.0,
          "Medical Allowance": 300.0
        },
        "deductions": {
          "Tax": 9600.0,
          "Insurance": 150.0,
          "Pension": 4000.0
        },
        "net_salary": 79050.0,
        "generated_date": "2025-07-27T22:02:03.457933"
      },
      {
        "slip_id": "SS202504TCH005",
        "teacher_id": "TCH005",
        "month": "April",
        "year": 2025,
        "basic_salary": 80000,
        "allowances": {
          "Housing Allowance": 12000.0,
          "Transport Allowance": 500.0,
          "Medical Allowance": 300.0
        },
        "deductions": {
          "Tax": 9600.0,
          "Insurance": 150.0,
          "Pension": 4000.0
        },
        "net_salary": 79050.0,
        "generated_date": "2025-07-27T22:02:03.457938"
      }
    ],
    "profile_updates": []
  },
  {
    "username": "teacher6",
    "password": "63cb9c6fa2d65784658539a93ad47f2274a02ddff344537beb97bd399938ad22",
    "name": "Professor 6",
    "email": "teacher6@portal.edu",
    "user_id": "TCH006",
    "user_type": "Teacher",
    "last_login": null,
    "teacher_id": "TCH006",
    "department": "Computer Science",
    "qualification": "PhD",
    "contact_info": {
      "office_room": "Room 106",
      "office_building": "Science Building",
      "office_hours": "Mon-Wed 2-4 PM",
      "personal_phone": "555-1006"
    },
    "salary": 81000,
    "courses_taught": [],
    "salary_slips": [
      {
        "slip_id": "SS202501TCH006",
        "teacher_id": "TCH006",
        "month": "January",
        "year": 2025,
        "basic_salary": 81000,
        "allowances": {
          "Housing Allowance": 12150.0,
          "Transport Allowance": 500.0,
          "Medical Allowance": 300.0
        },
        "deductions": {
          "Tax": 9720.0,
          "Insurance": 150.0,
          "Pension": 4050.0
        },
        "net_salary": 80030.0,
        "generated_date": "2025-07-27T22:02:03.457991"
      },
      {
        "slip_id": "SS202502TCH006",
        "teacher_id": "TCH006",
        "month": "February",
        "year": 2025,
        "basic_salary": 81000,
        "allowances": {
          "Housing Allowance": 12150.0,
          "Transport Allowance": 500.0,
          "Medical Allowance": 300.0
        },
        "deductions": {
          "Tax": 9720.0,
          "Insurance": 150.0,
          "Pension": 4050.0
        },
        "net_salary": 80030.0,
        "generated_date": "2025-07-27T22:02:03.457998"
      },
      {
        "slip_id": "SS202503TCH006",
        "teacher_id": "TCH006",
        "month": "March",
        "year": 2025,
        "basic_salary": 81000,
        "allowances": {
          "Housing Allowance": 12150.0,
          "Transport Allowance": 500.0,
          "Medical Allowance": 300.0
        },
        "deductions": {
          "Tax": 9720.0,
          "Insurance": 150.0,
          "Pension": 4050.0
        },
        "net_salary": 80030.0,
        "generated_date": "2025-07-27T22:02:03.458003"
      },
      {
        "slip_id": "SS202504TCH006",
        "teacher_id": "TCH006",
        "month": "April",
        "year": 2025,
        "basic_salary": 81000,
        "allowances": {
          "Housing Allowance": 12150.0,
          "Transport Allowance": 500.0,
          "Medical Allowance": 300.0
        },
        "deductions": {
          "Tax": 9720.0,
          "Insurance": 150.0,
          "Pension": 4050.0
        },
        "net_salary": 80030.0,
        "generated_date": "2025-07-27T22:02:03.458005"
      }
    ],
    "profile_updates": []
  },
  {
    "username": "teacher7",
    "password": "63cb9c6fa2d65784658539a93ad47f2274a02ddff344537beb97bd399938ad22",
    "name": "Professor 7",
    "email": "teacher7@portal.edu",
    "user_id": "TCH007",
    "user_type": "Teacher",
    "last_login": null,
    "teacher_id": "TCH007",
    "department": "Mathematics",
    "qualification": "PhD",
    "contact_info": {
      "office_room": "Room 107",
      "office_building": "Math Building",
      "office_hours": "Mon-Wed 2-4 PM",
      "personal_phone": "555-1007"
    },
    "salary": 82000,
    "courses_taught": [],
    "salary_slips": [
      {
        "slip_id": "SS202501TCH007",
        "teacher_id": "TCH007",
        "month": "January",
        "year": 2025,
        "basic_salary": 82000,
        "allowances": {
          "Housing Allowance": 12300.0,
          "Transport Allowance": 500.0,
          "Medical Allowance": 300.0
        },
        "deductions": {
          "Tax": 9840.0,
          "Insurance": 150.0,
          "Pension": 4100.0
        },
        "net_salary": 81010.0,
        "generated_date": "2025-07-27T22:02:03.458043"
      },
      {
        "slip_id": "SS202502TCH007",
        "teacher_id": "TCH007",
        "month": "February",
        "year": 2025,
        "basic_salary": 82000,
        "allowances": {
          "Housing Allowance": 12300.0,
          "Transport Allowance": 500.0,
          "Medical Allowance": 300.0
        },
        "deductions": {
          "Tax": 9840.0,
          "Insurance": 150.0,
          "Pension": 4100.0
        },
        "net_salary": 81010.0,
        "generated_date": "2025-07-27T22:02:03.458048"
      },
      {
        "slip_id": "SS202503TCH007",
        "teacher_id": "TCH007",
        "month": "March",
        "year": 2025,
        "basic_salary": 82000,
        "allowances": {
          "Housing Allowance": 12300.0,
          "Transport Allowance": 500.0,
          "Medical Allowance": 300.0
        },
        "deductions": {
          "Tax": 9840.0,
          "Insurance": 150.0,
          "Pension": 4100.0
        },
        "net_salary": 81010.0,
        "generated_date": "2025-07-27T22:02:03.458051"
      },
      {
        "slip_id": "SS202504TCH007",
        "teacher_id": "TCH007",
        "month": "April",
        "year": 2025,
        "basic_salary": 82000,
        "allowances": {
          "Housing Allowance": 12300.0,
          "Transport Allowance": 500.0,
          "Medical Allowance": 300.0
        },
        "deductions": {
          "Tax": 9840.0,
          "Insurance": 150.0,
          "Pension": 4100.0
        },
        "net_salary": 81010.0,
        "generated_date": "2025-07-27T22:02:03.458053"
      }
    ],
    "profile_updates": []
  },
  {
    "username": "teacher8",
    "password": "63cb9c6fa2d65784658539a93ad47f2274a02ddff344537beb97bd399938ad22",
    "name": "Professor 8",
    "email": "teacher8@portal.edu",
    "user_id": "TCH008",
    "user_type": "Teacher",
    "last_login": null,
    "teacher_id": "TCH008",
    "department": "Physics",
    "qualification": "PhD",
    "contact_info": {
      "office_room": "Room 108",
      "office_building": "Physics Lab",
      "office_hours": "Mon-Wed 2-4 PM",
      "personal_phone": "555-1008"
    },
    "salary": 83000,
    "courses_taught": [],
    "salary_slips": [
      {
        "slip_id": "SS202501TCH008",
        "teacher_id": "TCH008",
        "month": "January",
        "year": 2025,
        "basic_salary": 83000,
        "allowances": {
          "Housing Allowance": 12450.0,
          "Transport Allowance": 500.0,
          "Medical Allowance": 300.0
        },
        "deductions": {
          "Tax": 9960.0,
          "Insurance": 150.0,
          "Pension": 4150.0
        },
        "net_salary": 81990.0,
        "generated_date": "2025-07-27T22:02:03.458092"
      },
      {
        "slip_id": "SS202502TCH008",
        "teacher_id": "TCH008",
        "month": "February",
        "year": 2025,
        "basic_salary": 83000,
        "allowances": {
          "Housing Allowance": 12450.0,
          "Transport Allowance": 500.0,
          "Medical Allowance": 300.0
        },
        "deductions": {
          "Tax": 9960.0,
          "Insurance": 150.0,
          "Pension": 4150.0
        },
        "net_salary": 81990.0,
        "generated_date": "2025-07-27T22:02:03.458095"
      },
      {
        "slip_id": "SS202503TCH008",
        "teacher_id": "TCH008",
        "month": "March",
        "year": 2025,
        "basic_salary": 83000,
        "allowances": {
          "Housing Allowance": 12450.0,
          "Transport Allowance": 500.0,
          "Medical Allowance": 300.0
        },
        "deductions": {
          "Tax": 9960.0,
          "Insurance": 150.0,
          "Pension": 4150.0
        },
        "net_salary": 81990.0,
        "generated_date": "2025-07-27T22:02:03.458097"
      },
      {
        "slip_id": "SS202504TCH008",
        "teacher_id": "TCH008",
        "month": "April",
        "year": 2025,
        "basic_salary": 83000,
        "allowances": {
          "Housing Allowance": 12450.0,
          "Transport Allowance": 500.0,
          "Medical Allowance": 300.0
        },
        "deductions": {
          "Tax": 9960.0,
          "Insurance": 150.0,
          "Pension": 4150.0
        },
        "net_salary": 81990.0,
        "generated_date": "2025-07-27T22:02:03.458099"
      }
    ],
    "profile_updates": []
  },
  {
    "username": "teacher9",
    "password": "63cb9c6fa2d65784658539a93ad47f2274a02ddff344537beb97bd399938ad22",
    "name": "Professor 9",
    "email": "teacher9@portal.edu",
    "user_id": "TCH009",
    "user_type": "Teacher",
    "last_login": null,
    "teacher_id": "TCH009",
    "department": "English",
    "qualification": "PhD",
    "contact_info": {
      "office_room": "Room 109",
      "office_building": "Liberal Arts",
      "office_hours": "Mon-Wed 2-4 PM",
      "personal_phone": "555-1009"
    },
    "salary": 84000,
    "courses_taught": [],
    "salary_slips": [
      {
        "slip_id": "SS202501TCH009",
        "teacher_id": "TCH009",
        "month": "January",
        "year": 2025,
        "basic_salary": 84000,
        "allowances": {
          "Housing Allowance": 12600.0,
          "Transport Allowance": 500.0,
          "Medical Allowance": 300.0
        },
        "deductions": {
          "Tax": 10080.0,
          "Insurance": 150.0,
          "Pension": 4200.0
        },
        "net_salary": 82970.0,
        "generated_date": "2025-07-27T22:02:03.458134"
      },
      {
        "slip_id": "SS202502TCH009",
        "teacher_id": "TCH009",
        "month": "February",
        "year": 2025,
        "basic_salary": 84000,
        "allowances": {
          "Housing Allowance": 12600.0,
          "Transport Allowance": 500.0,
          "Medical Allowance": 300.0
        },
        "deductions": {
          "Tax": 10080.0,
          "Insurance": 150.0,
          "Pension": 4200.0
        },
        "net_salary": 82970.0,
        "generated_date": "2025-07-27T22:02:03.458139"
      },
      {
        "slip_id": "SS202503TCH009",
        "teacher_id": "TCH009",
        "month": "March",
        "year": 2025,
        "basic_salary": 84000,
        "allowances": {
          "Housing Allowance": 12600.0,
          "Transport Allowance": 500.0,
          "Medical Allowance": 300.0
        },
        "deductions": {
          "Tax": 10080.0,
          "Insurance": 150.0,
          "Pension": 4200.0
        },
        "net_salary": 82970.0,
        "generated_date": "2025-07-27T22:02:03.458142"
      },
      {
        "slip_id": "SS202504TCH009",
        "teacher_id": "TCH009",
        "month": "April",
        "year": 2025,
        "basic_salary": 84000,
        "allowances": {
          "Housing Allowance": 12600.0,
          "Transport Allowance": 500.0,
          "Medical Allowance": 300.0
        },
        "deductions": {
          "Tax": 10080.0,
          "Insurance": 150.0,
          "Pension": 4200.0
        },
        "net_salary": 82970.0,
        "generated_date": "2025-07-27T22:02:03.458144"
      }
    ],
    "profile_updates": []
  },
  {
    "username": "teacher10",
    "password": "63cb9c6fa2d65784658539a93ad47f2274a02ddff344537beb97bd399938ad22",
    "name": "Professor 10",
    "email": "teacher10@portal.edu",
    "user_id": "TCH010",
    "user_type": "Teacher",
    "last_login": null,
    "teacher_id": "TCH010",
    "department": "Business",
    "qualification": "PhD",
    "contact_info": {
      "office_room": "Room 110",
      "office_building": "Business Center",
      "office_hours": "Mon-Wed 2-4 PM",
      "personal_phone": "555-1010"
    },
    "salary": 85000,
    "courses_taught": [],
    "salary_slips": [
      {
        "slip_id": "SS202501TCH010",
        "teacher_id": "TCH010",
        "month": "January",
        "year": 2025,
        "basic_salary": 85000,
        "allowances": {
          "Housing Allowance": 12750.0,
          "Transport Allowance": 500.0,
          "Medical Allowance": 300.0
        },
        "deductions": {
          "Tax": 10200.0,
          "Insurance": 150.0,
          "Pension": 4250.0
        },
        "net_salary": 83950.0,
        "generated_date": "2025-07-27T22:02:03.458194"
      },
      {
        "slip_id": "SS202502TCH010",
        "teacher_id": "TCH010",
        "month": "February",
        "year": 2025,
        "basic_salary": 85000,
        "allowances": {
          "Housing Allowance": 12750.0,
          "Transport Allowance": 500.0,
          "Medical Allowance": 300.0
        },
        "deductions": {
          "Tax": 10200.0,
          "Insurance": 150.0,
          "Pension": 4250.0
        },
        "net_salary": 83950.0,
        "generated_date": "2025-07-27T22:02:03.458200"
      },
      {
        "slip_id": "SS202503TCH010",
        "teacher_id": "TCH010",
        "month": "March",
        "year": 2025,
        "basic_salary": 85000,
        "allowances": {
          "Housing Allowance": 12750.0,
          "Transport Allowance": 500.0,
          "Medical Allowance": 300.0
        },
        "deductions": {
          "Tax": 10200.0,
          "Insurance": 150.0,
          "Pension": 4250.0
        },
        "net_salary": 83950.0,
        "generated_date": "2025-07-27T22:02:03.458205"
      },
      {
        "slip_id": "SS202504TCH010",
        "teacher_id": "TCH010",
        "month": "April",
        "year": 2025,
        "basic_salary": 85000,
        "allowances": {
          "Housing Allowance": 12750.0,
          "Transport Allowance": 500.0,
          "Medical Allowance": 300.0
        },
        "deductions": {
          "Tax": 10200.0,
          "Insurance": 150.0,
          "Pension": 4250.0
        },
        "net_salary": 83950.0,
        "generated_date": "2025-07-27T22:02:03.458207"
      }
    ],
    "profile_updates": []
  },
  {
    "username": "teacher11",
    "password": "63cb9c6fa2d65784658539a93ad47f2274a02ddff344537beb97bd399938ad22",
    "name": "Professor 11",
    "email": "teacher11@portal.edu",
    "user_id": "TCH011",
    "user_type": "Teacher",
    "last_login": null,
    "teacher_id": "TCH011",
    "department": "Computer Science",
    "qualification": "PhD",
    "contact_info": {
      "office_room": "Room 111",
      "office_building": "Science Building",
      "office_hours": "Mon-Wed 2-4 PM",
      "personal_phone": "555-1011"
    },
    "salary": 86000,
    "courses_taught": [],
    "salary_slips": [
      {
        "slip_id": "SS202501TCH011",
        "teacher_id": "TCH011",
        "month": "January",
        "year": 2025,
        "basic_salary": 86000,
        "allowances": {
          "Housing Allowance": 12900.0,
          "Transport Allowance": 500.0,
          "Medical Allowance": 300.0
        },
        "deductions": {
          "Tax": 10320.0,
          "Insurance": 150.0,
          "Pension": 4300.0
        },
        "net_salary": 84930.0,
        "generated_date": "2025-07-27T22:02:03.458251"
      },
      {
        "slip_id": "SS202502TCH011",
        "teacher_id": "TCH011",
        "month": "February",
        "year": 2025,
        "basic_salary": 86000,
        "allowances": {
          "Housing Allowance": 12900.0,
          "Transport Allowance": 500.0,
          "Medical Allowance": 300.0
        },
        "deductions": {
          "Tax": 10320.0,
          "Insurance": 150.0,
          "Pension": 4300.0
        },
        "net_salary": 84930.0,
        "generated_date": "2025-07-27T22:02:03.458260"
      },
      {
        "slip_id": "SS202503TCH011",
        "teacher_id": "TCH011",
        "month": "March",
        "year": 2025,
        "basic_salary": 86000,
        "allowances": {
          "Housing Allowance": 12900.0,
          "Transport Allowance": 500.0,
          "Medical Allowance": 300.0
        },
        "deductions": {
          "Tax": 10320.0,
          "Insurance": 150.0,
          "Pension": 4300.0
        },
        "net_salary": 84930.0,
        "generated_date": "2025-07-27T22:02:03.458263"
      },
      {
        "slip_id": "SS202504TCH011",
        "teacher_id": "TCH011",
        "month": "April",
        "year": 2025,
        "basic_salary": 86000,
        "allowances": {
          "Housing Allowance": 12900.0,
          "Transport Allowance": 500.0,
          "Medical Allowance": 300.0
        },
        "deductions": {
          "Tax": 10320.0,
          "Insurance": 150.0,
          "Pension": 4300.0
        },
        "net_salary": 84930.0,
        "generated_date": "2025-07-27T22:02:03.458265"
      }
    ],
    "profile_updates": []
  },
  {
    "username": "teacher12",
    "password": "63cb9c6fa2d65784658539a93ad47f2274a02ddff344537beb97bd399938ad22",
    "name": "Professor 12",
    "email": "teacher12@portal.edu",
    "user_id": "TCH012",
    "user_type": "Teacher",
    "last_login": null,
    "teacher_id": "TCH012",
    "department": "Mathematics",
    "qualification": "PhD",
    "contact_info": {
      "office_room": "Room 112",
      "office_building": "Math Building",
      "office_hours": "Mon-Wed 2-4 PM",
      "personal_phone": "555-1012"
    },
    "salary": 87000,
    "courses_taught": [],
    "salary_slips": [
      {
        "slip_id": "SS202501TCH012",
        "teacher_id": "TCH012",
        "month": "January",
        "year": 2025,
        "basic_salary": 87000,
        "allowances": {
          "Housing Allowance": 13050.0,
          "Transport Allowance": 500.0,
          "Medical Allowance": 300.0
        },
        "deductions": {
          "Tax": 10440.0,
          "Insurance": 150.0,
          "Pension": 4350.0
        },
        "net_salary": 85910.0,
        "generated_date": "2025-07-27T22:02:03.458312"
      },
      {
        "slip_id": "SS202502TCH012",
        "teacher_id": "TCH012",
        "month": "February",
        "year": 2025,
        "basic_salary": 87000,
        "allowances": {
          "Housing Allowance": 13050.0,
          "Transport Allowance": 500.0,
          "Medical Allowance": 300.0
        },
        "deductions": {
          "Tax": 10440.0,
          "Insurance": 150.0,
          "Pension": 4350.0
        },
        "net_salary": 85910.0,
        "generated_date": "2025-07-27T22:02:03.458318"
      },
      {
        "slip_id": "SS202503TCH012",
        "teacher_id": "TCH012",
        "month": "March",
        "year": 2025,
        "basic_salary": 87000,
        "allowances": {
          "Housing Allowance": 13050.0,
          "Transport Allowance": 500.0,
          "Medical Allowance": 300.0
        },
        "deductions": {
          "Tax": 10440.0,
          "Insurance": 150.0,
          "Pension": 4350.0
        },
        "net_salary": 85910.0,
        "generated_date": "2025-07-27T22:02:03.458322"
      },
      {
        "slip_id": "SS202504TCH012",
        "teacher_id": "TCH012",
        "month": "April",
        "year": 2025,
        "basic_salary": 87000,
        "allowances": {
          "Housing Allowance": 13050.0,
          "Transport Allowance": 500.0,
          "Medical Allowance": 300.0
        },
        "deductions": {
          "Tax": 10440.0,
          "Insurance": 150.0,
          "Pension": 4350.0
        },
        "net_salary": 85910.0,
        "generated_date": "2025-07-27T22:02:03.458324"
      }
    ],
    "profile_updates": []
  },
  {
    "username": "teacher13",
    "password": "63cb9c6fa2d65784658539a93ad47f2274a02ddff344537beb97bd399938ad22",
    "name": "Professor 13",
    "email": "teacher13@portal.edu",
    "user_id": "TCH013",
    "user_type": "Teacher",
    "last_login": null,
    "teacher_id": "TCH013",
    "department": "Physics",
    "qualification": "PhD",
    "contact_info": {
      "office_room": "Room 113",
      "office_building": "Physics Lab",
      "office_hours": "Mon-Wed 2-4 PM",
      "personal_phone": "555-1013"
    },
    "salary": 88000,
    "courses_taught": [],
    "salary_slips": [
      {
        "slip_id": "SS202501TCH013",
        "teacher_id": "TCH013",
        "month": "January",
        "year": 2025,
        "basic_salary": 88000,
        "allowances": {
          "Housing Allowance": 13200.0,
          "Transport Allowance": 500.0,
          "Medical Allowance": 300.0
        },
        "deductions": {
          "Tax": 10560.0,
          "Insurance": 150.0,
          "Pension": 4400.0
        },
        "net_salary": 86890.0,
        "generated_date": "2025-07-27T22:02:03.458364"
      },
      {
        "slip_id": "SS202502TCH013",
        "teacher_id": "TCH013",
        "month": "February",
        "year": 2025,
        "basic_salary": 88000,
        "allowances": {
          "Housing Allowance": 13200.0,
          "Transport Allowance": 500.0,
          "Medical Allowance": 300.0
        },
        "deductions": {
          "Tax": 10560.0,
          "Insurance": 150.0,
          "Pension": 4400.0
        },
        "net_salary": 86890.0,
        "generated_date": "2025-07-27T22:02:03.458370"
      },
      {
        "slip_id": "SS202503TCH013",
        "teacher_id": "TCH013",
        "month": "March",
        "year": 2025,
        "basic_salary": 88000,
        "allowances": {
          "Housing Allowance": 13200.0,
          "Transport Allowance": 500.0,
          "Medical Allowance": 300.0
        },
        "deductions": {
          "Tax": 10560.0,
          "Insurance": 150.0,
          "Pension": 4400.0
        },
        "net_salary": 86890.0,
        "generated_date": "2025-07-27T22:02:03.458373"
      },
      {
        "slip_id": "SS202504TCH013",
        "teacher_id": "TCH013",
        "month": "April",
        "year": 2025,
        "basic_salary": 88000,
        "allowances": {
          "Housing Allowance": 13200.0,
          "Transport Allowance": 500.0,
          "Medical Allowance": 300.0
        },
        "deductions": {
          "Tax": 10560.0,
          "Insurance": 150.0,
          "Pension": 4400.0
        },
        "net_salary": 86890.0,
        "generated_date": "2025-07-27T22:02:03.458376"
      }
    ],
    "profile_updates": []
  },
  {
    "username": "teacher14",
    "password": "63cb9c6fa2d65784658539a93ad47f2274a02ddff344537beb97bd399938ad22",
    "name": "Professor 14",
    "email": "teacher14@portal.edu",
    "user_id": "TCH014",
    "user_type": "Teacher",
    "last_login": null,
    "teacher_id": "TCH014",
    "department": "English",
    "qualification": "PhD",
    "contact_info": {
      "office_room": "Room 114",
      "office_building": "Liberal Arts",
      "office_hours": "Mon-Wed 2-4 PM",
      "personal_phone": "555-1014"
    },
    "salary": 89000,
    "courses_taught": [],
    "salary_slips": [
      {
        "slip_id": "SS202501TCH014",
        "teacher_id": "TCH014",
        "month": "January",
        "year": 2025,
        "basic_salary": 89000,
        "allowances": {
          "Housing Allowance": 13350.0,
          "Transport Allowance": 500.0,
          "Medical Allowance": 300.0
        },
        "deductions": {
          "Tax": 10680.0,
          "Insurance": 150.0,
          "Pension": 4450.0
        },
        "net_salary": 87870.0,
        "generated_date": "2025-07-27T22:02:03.458414"
      },
      {
        "slip_id": "SS202502TCH014",
        "teacher_id": "TCH014",
        "month": "February",
        "year": 2025,
        "basic_salary": 89000,
        "allowances": {
          "Housing Allowance": 13350.0,
          "Transport Allowance": 500.0,
          "Medical Allowance": 300.0
        },
        "deductions": {
          "Tax": 10680.0,
          "Insurance": 150.0,
          "Pension": 4450.0
        },
        "net_salary": 87870.0,
        "generated_date": "2025-07-27T22:02:03.458418"
      },
      {
        "slip_id": "SS202503TCH014",
        "teacher_id": "TCH014",
        "month": "March",
        "year": 2025,
        "basic_salary": 89000,
        "allowances": {
          "Housing Allowance": 13350.0,
          "Transport Allowance": 500.0,
          "Medical Allowance": 300.0
        },
        "deductions": {
          "Tax": 10680.0,
          "Insurance": 150.0,
          "Pension": 4450.0
        },
        "net_salary": 87870.0,
        "generated_date": "2025-07-27T22:02:03.458423"
      },
      {
        "slip_id": "SS202504TCH014",
        "teacher_id": "TCH014",
        "month": "April",
        "year": 2025,
        "basic_salary": 89000,
        "allowances": {
          "Housing Allowance": 13350.0,
          "Transport Allowance": 500.0,
          "Medical Allowance": 300.0
        },
        "deductions": {
          "Tax": 10680.0,
          "Insurance": 150.0,
          "Pension": 4450.0
        },
        "net_salary": 87870.0,
        "generated_date": "2025-07-27T22:02:03.458426"
      }
    ],
    "profile_updates": []
  },
  {
    "username": "teacher15",
    "password": "63cb9c6fa2d65784658539a93ad47f2274a02ddff344537beb97bd399938ad22",
    "name": "Professor 15",
    "email": "teacher15@portal.edu",
    "user_id": "TCH015",
    "user_type": "Teacher",
    "last_login": null,
    "teacher_id": "TCH015",
    "department": "Business",
    "qualification": "PhD",
    "contact_info": {
      "office_room": "Room 115",
      "office_building": "Business Center",
      "office_hours": "Mon-Wed 2-4 PM",
      "personal_phone": "555-1015"
    },
    "salary": 90000,
    "courses_taught": [],
    "salary_slips": [
      {
        "slip_id": "SS202501TCH015",
        "teacher_id": "TCH015",
        "month": "January",
        "year": 2025,
        "basic_salary": 90000,
        "allowances": {
          "Housing Allowance": 13500.0,
          "Transport Allowance": 500.0,
          "Medical Allowance": 300.0
        },
        "deductions": {
          "Tax": 10800.0,
          "Insurance": 150.0,
          "Pension": 4500.0
        },
        "net_salary": 88850.0,
        "generated_date": "2025-07-27T22:02:03.458473"
      },
      {
        "slip_id": "SS202502TCH015",
        "teacher_id": "TCH015",
        "month": "February",
        "year": 2025,
        "basic_salary": 90000,
        "allowances": {
          "Housing Allowance": 13500.0,
          "Transport Allowance": 500.0,
          "Medical Allowance": 300.0
        },
        "deductions": {
          "Tax": 10800.0,
          "Insurance": 150.0,
          "Pension": 4500.0
        },
        "net_salary": 88850.0,
        "generated_date": "2025-07-27T22:02:03.458477"
      },
      {
        "slip_id": "SS202503TCH015",
        "teacher_id": "TCH015",
        "month": "March",
        "year": 2025,
        "basic_salary": 90000,
        "allowances": {
          "Housing Allowance": 13500.0,
          "Transport Allowance": 500.0,
          "Medical Allowance": 300.0
        },
        "deductions": {
          "Tax": 10800.0,
          "Insurance": 150.0,
          "Pension": 4500.0
        },
        "net_salary": 88850.0,
        "generated_date": "2025-07-27T22:02:03.458479"
      },
      {
        "slip_id": "SS202504TCH015",
        "teacher_id": "TCH015",
        "month": "April",
        "year": 2025,
        "basic_salary": 90000,
        "allowances": {
          "Housing Allowance": 13500.0,
          "Transport Allowance": 500.0,
          "Medical Allowance": 300.0
        },
        "deductions": {
          "Tax": 10800.0,
          "Insurance": 150.0,
          "Pension": 4500.0
        },
        "net_salary": 88850.0,
        "generated_date": "2025-07-27T22:02:03.458482"
      }
    ],
    "profile_updates": []
  },
  {
    "username": "student275650",
    "password": "aPKQ6yOb",
    "name": "studentt",
    "email": "studentt@uol.pk",
    "user_id": "STU202507275650",
    "user_type": "Student",
    "last_login": null,
    "student_id": "STU202507275650",
    "enrolled_courses": [],
    "academic_records": {},
    "cgpa_history": [],
    "semester_data": {}
  },
  {
    "username": "teacher270705",
    "password": "Od1duXb1",
    "name": "teacher16",
    "email": "teacher16@gmail.com",
    "user_id": "TEA202507270705",
    "user_type": "Teacher",
    "last_login": null,
    "teacher_id": "TEA202507270705",
    "department": "english",
    "qualification": "",
    "contact_info": {},
    "salary": 84000.0,
    "courses_taught": [],
    "salary_slips": [],
    "profile_updates": []
  },
  {
    "username": "teacher277218",
    "password": "SA9SrrHM",
    "name": "teacher17",
    "email": "teacher17@gmail.com",
    "user_id": "TEA202507277218",
    "user_type": "Teacher",
    "last_login": null,
    "teacher_id": "TEA202507277218",
    "department": "computer",
    "qualification": "",
    "contact_info": {},
    "salary": -24000.0,
    "courses_taught": [],
    "salary_slips": [],
    "profile_updates": []
  },
  {
    "username": "student272843",
    "password": "I7qe7RKa",
    "name": "1",
    "email": "1",
    "user_id": "STU202507272843",
    "user_type": "Student",
    "last_login": null,
    "student_id": "STU202507272843",
    "enrolled_courses": [],
    "academic_records": {},
    "cgpa_history": [],
    "semester_data": {}
  },
  {
    "username": "student275199",
    "password": "IGJfCyBd",
    "name": "Test Student",
    "email": "teststudent@example.com",
    "user_id": "STU202507275199",
    "user_type": "Student",
    "last_login": null,
    "student_id": "STU202507275199",
    "enrolled_courses": [],
    "academic_records": {},
    "cgpa_history": [],
    "semester_data": {}
  },
  {
    "username": "teacher275948",
    "password": "HrM6Otc6",
    "name": "teacher18",
    "email": "teacher18@gmail.com",
    "user_id": "TEA202507275948",
    "user_type": "Teacher",
    "last_login": null,
    "teacher_id": "TEA202507275948",
    "department": "arts",
    "qualification": "",
    "contact_info": {},
    "salary": 10000000.0,
    "courses_taught": [],
    "salary_slips": [],
    "profile_updates": []
  }
]